{
    "category": "sheets", 
    "changes": "Initial version", 
    "description": "", 
    "files": {
        "first-sheet-1": {
            "asset": "https://d2mgbjyendvdw0.cloudfront.net/03020/0326/NEW_LEN_OOD_MDR_C-ST_A-SA_M-AP_cad-1_18.00-0.0.dxf", 
            "name": "First Sheet", 
            "num_sheets": 1.0
        }, 
        "second-sheet-2": {
            "asset": "https://d2mgbjyendvdw0.cloudfront.net/03021/0326/NEW_LEN_OOD_MDR_C-ST_A-SA_M-AP_cad-2_18.00-0.0.dxf", 
            "name": "Second Sheet", 
            "num_sheets": 1.0
        }
    }, 
    "manufacturing": {
        "cutting": {
            "total_sheets": 2.0
        }, 
        "strategies": {
            "A": {
                "sheets": [
                    {
                        "sheet": {
                            "asset": "https://d2mgbjyendvdw0.cloudfront.net/03020/0326/NEW_LEN_OOD_MDR_C-ST_A-SA_M-AP_cad-1_18.00-0.0.dxf", 
                            "name": "First Sheet", 
                            "num_sheets": 1.0
                        }, 
                        "use": {
                            "changes": "Initial version", 
                            "description": "Sheet materials in the Opendesk taxonomy.", 
                            "name": "Sheets", 
                            "options": {}, 
                            "path": "/materials/opendesk/sheets", 
                            "schema": "https://opendesk.cc/schemata/material.json", 
                            "source": "https://opendesk.herokuapp.com/api/v1/open", 
                            "type": "material", 
                            "version": [
                                1, 
                                0, 
                                0
                            ]
                        }
                    }, 
                    {
                        "sheet": {
                            "asset": "https://d2mgbjyendvdw0.cloudfront.net/03021/0326/NEW_LEN_OOD_MDR_C-ST_A-SA_M-AP_cad-2_18.00-0.0.dxf", 
                            "name": "Second Sheet", 
                            "num_sheets": 1.0
                        }, 
                        "use": {
                            "changes": "Initial version", 
                            "description": "Sheet materials in the Opendesk taxonomy.", 
                            "name": "Sheets", 
                            "options": {}, 
                            "path": "/materials/opendesk/sheets", 
                            "schema": "https://opendesk.cc/schemata/material.json", 
                            "source": "https://opendesk.herokuapp.com/api/v1/open", 
                            "type": "material", 
                            "version": [
                                1, 
                                0, 
                                0
                            ]
                        }
                    }
                ], 
                "type": "string", 
                "value": "A"
            }
        }
    }, 
    "name": "Plywood", 
    "options": {
        "*/material": [
            {
                "$ref": "/materials/opendesk/sheets", 
                "options": {
                    "strategy": {
                        "default": "A", 
                        "scopes": [
                            "maker", 
                            "operator"
                        ], 
                        "type": "set::string", 
                        "values": [
                            "$ref:~/manufacturing/strategies/A"
                        ]
                    }
                }
            }
        ]
    }, 
    "path": "/ranges/lean/office-olivia/1450x750/plywood", 
    "schema": "https://opendesk.cc/schemata/fileset.json", 
    "source": "https://opendesk.herokuapp.com/api/v1/open", 
    "type": "fileset", 
    "version": [
        1, 
        0, 
        0
    ]
}